hwinfo_tui/__init__.py
hwinfo_tui/cli.py
hwinfo_tui/main.py
hwinfo_tui/data/__init__.py
hwinfo_tui/data/csv_reader.py
hwinfo_tui/data/sensors.py
hwinfo_tui/display/__init__.py
hwinfo_tui/display/chart.py
hwinfo_tui/display/layout.py
hwinfo_tui/display/table.py
hwinfo_tui/utils/__init__.py
hwinfo_tui/utils/config.py
hwinfo_tui/utils/logging.py
hwinfo_tui/utils/stats.py
hwinfo_tui/utils/units.py
hwinfo_tui-1.0.1.dist-info/licenses/LICENSE
hwinfo_tui-1.0.1.dist-info/METADATA
hwinfo_tui-1.0.1.dist-info/WHEEL
hwinfo_tui-1.0.1.dist-info/entry_points.txt
hwinfo_tui-1.0.1.dist-info/top_level.txt
hwinfo_tui-1.0.1.dist-info/RECORD
