Metadata-Version: 2.4
Name: hwinfo-tui
Version: 1.0.1
Summary: A gping-inspired terminal visualization tool for monitoring real-time hardware sensor data from HWInfo
Author: JuanjoFuchs
License: MIT
Project-URL: Homepage, https://github.com/JuanjoFuchs/hwinfo-tui
Project-URL: Issues, https://github.com/JuanjoFuchs/hwinfo-tui/issues
Project-URL: Repository, https://github.com/JuanjoFuchs/hwinfo-tui.git
Keywords: hardware,monitoring,tui,sensors,hwinfo,visualization
Classifier: Development Status :: 4 - Beta
Classifier: Environment :: Console
Classifier: Intended Audience :: System Administrators
Classifier: Operating System :: OS Independent
Classifier: Programming Language :: Python :: 3
Classifier: Programming Language :: Python :: 3.8
Classifier: Programming Language :: Python :: 3.9
Classifier: Programming Language :: Python :: 3.10
Classifier: Programming Language :: Python :: 3.11
Classifier: Programming Language :: Python :: 3.12
Classifier: Topic :: System :: Monitoring
Classifier: Topic :: System :: Hardware
Requires-Python: >=3.8
License-File: LICENSE
Requires-Dist: typer[all]>=0.9.0
Requires-Dist: rich>=13.0.0
Requires-Dist: plotext>=5.0.0
Requires-Dist: pandas>=1.5.0
Requires-Dist: watchdog>=3.0.0
Requires-Dist: toml>=0.10.2
Provides-Extra: dev
Requires-Dist: pytest>=7.0.0; extra == "dev"
Requires-Dist: pytest-cov>=4.0.0; extra == "dev"
Requires-Dist: black>=22.0.0; extra == "dev"
Requires-Dist: ruff>=0.1.0; extra == "dev"
Requires-Dist: mypy>=1.0.0; extra == "dev"
Requires-Dist: pre-commit>=2.20.0; extra == "dev"
Requires-Dist: build>=1.0.0; extra == "dev"
Requires-Dist: twine>=4.0.0; extra == "dev"
Requires-Dist: pyinstaller>=6.0.0; extra == "dev"
Requires-Dist: types-toml>=0.10.8; extra == "dev"
Requires-Dist: pandas-stubs>=2.0.0; extra == "dev"
Requires-Dist: importlib-metadata>=4.0.0; python_version < "3.8" and extra == "dev"
Dynamic: license-file
